odoo9_addon_stock_removal_location_by_priority-9.0.1.0.0.99.dev4-py2.7-nspkg.pth
odoo9_addon_stock_removal_location_by_priority-9.0.1.0.0.99.dev4.dist-info/DESCRIPTION.rst
odoo9_addon_stock_removal_location_by_priority-9.0.1.0.0.99.dev4.dist-info/METADATA
odoo9_addon_stock_removal_location_by_priority-9.0.1.0.0.99.dev4.dist-info/RECORD
odoo9_addon_stock_removal_location_by_priority-9.0.1.0.0.99.dev4.dist-info/WHEEL
odoo9_addon_stock_removal_location_by_priority-9.0.1.0.0.99.dev4.dist-info/metadata.json
odoo9_addon_stock_removal_location_by_priority-9.0.1.0.0.99.dev4.dist-info/namespace_packages.txt
odoo9_addon_stock_removal_location_by_priority-9.0.1.0.0.99.dev4.dist-info/top_level.txt
odoo_addons/stock_removal_location_by_priority/README.rst
odoo_addons/stock_removal_location_by_priority/__init__.py
odoo_addons/stock_removal_location_by_priority/__openerp__.py
odoo_addons/stock_removal_location_by_priority/init_hook.py
odoo_addons/stock_removal_location_by_priority/i18n/de.po
odoo_addons/stock_removal_location_by_priority/i18n/es.po
odoo_addons/stock_removal_location_by_priority/i18n/fi.po
odoo_addons/stock_removal_location_by_priority/i18n/fr.po
odoo_addons/stock_removal_location_by_priority/i18n/it.po
odoo_addons/stock_removal_location_by_priority/i18n/pt_BR.po
odoo_addons/stock_removal_location_by_priority/i18n/ro.po
odoo_addons/stock_removal_location_by_priority/i18n/sl.po
odoo_addons/stock_removal_location_by_priority/i18n/stock_removal_location_by_priority.pot
odoo_addons/stock_removal_location_by_priority/i18n/zh_CN.po
odoo_addons/stock_removal_location_by_priority/models/__init__.py
odoo_addons/stock_removal_location_by_priority/models/stock_location.py
odoo_addons/stock_removal_location_by_priority/models/stock_quant.py
odoo_addons/stock_removal_location_by_priority/static/description/icon.png
odoo_addons/stock_removal_location_by_priority/tests/__init__.py
odoo_addons/stock_removal_location_by_priority/tests/test_stock_removal_location_by_priority.py
odoo_addons/stock_removal_location_by_priority/views/stock_location_view.xml
